logistic_nlp_fitter/__init__.py
logistic_nlp_fitter/main.py
logistic_nlp_fitter/prompts.py
logistic_nlp_fitter-2025.12.21153404.dist-info/METADATA
logistic_nlp_fitter-2025.12.21153404.dist-info/WHEEL
logistic_nlp_fitter-2025.12.21153404.dist-info/top_level.txt
logistic_nlp_fitter-2025.12.21153404.dist-info/RECORD
