Metadata-Version: 2.4
Name: logistic-nlp-fitter
Version: 2025.12.21153404
Summary: A new package would help users fit logistic curves to their data by interpreting textual descriptions of datasets or growth scenarios. It would take natural language input (e.g., 'I have data showing
Author-email: logistic-nlp-fitter <hi@eugene.plus>
License: MIT
Project-URL: Homepage, https://github.com/chigwell/logistic-nlp-fitter
Requires-Python: >=3.9
Requires-Dist: langchain-llm7>=0.0.0
Requires-Dist: llmatch-messages>=0.0.0
Requires-Dist: langchain-core>=0.3.0
